codecov_ribs-0.1.18.dist-info/METADATA
codecov_ribs-0.1.18.dist-info/WHEEL
codecov_ribs-0.1.18.dist-info/license_files/LICENSE
cc_rustyribs/__init__.py
codecov_ribs_rs/__init__.py
codecov_ribs_rs/codecov_ribs_rs.abi3.so
codecov_ribs-0.1.18.dist-info/RECORD
