Metadata-Version: 2.1
Name: codecov-ribs
Version: 0.1.18
Classifier: Programming Language :: Rust
Classifier: Programming Language :: Python :: Implementation :: CPython
Classifier: Programming Language :: Python :: Implementation :: PyPy
License-File: LICENSE
Author: Thiago Ramos <thiago@codecov.io>
Author-email: Codecov <support@codecov.io>
License: BuSL-1.1
Requires-Python: >=3.8
